MANIFEST.in
setup.py
patchelf/.git
patchelf/.gitignore
patchelf/BUGS
patchelf/COPYING
patchelf/Makefile
patchelf/Makefile.am
patchelf/Makefile.in
patchelf/README
patchelf/aclocal.m4
patchelf/bootstrap.sh
patchelf/config.log
patchelf/config.status
patchelf/configure
patchelf/configure.ac
patchelf/patchelf.1
patchelf/patchelf.spec
patchelf/patchelf.spec.in
patchelf/release.nix
patchelf/version
patchelf/autom4te.cache/output.0
patchelf/autom4te.cache/output.1
patchelf/autom4te.cache/requests
patchelf/autom4te.cache/traces.0
patchelf/autom4te.cache/traces.1
patchelf/build-aux/compile
patchelf/build-aux/depcomp
patchelf/build-aux/install-sh
patchelf/build-aux/missing
patchelf/build-aux/test-driver
patchelf/src/Makefile
patchelf/src/Makefile.am
patchelf/src/Makefile.in
patchelf/src/elf.h
patchelf/src/patchelf
patchelf/src/patchelf.cc
patchelf/src/patchelf.o
patchelf/src/.deps/patchelf.Po
patchelf/tests/Makefile
patchelf/tests/Makefile.am
patchelf/tests/Makefile.in
patchelf/tests/bar.c
patchelf/tests/big-dynstr.sh
patchelf/tests/foo.c
patchelf/tests/main.c
patchelf/tests/no-rpath-prebuild.sh
patchelf/tests/no-rpath.c
patchelf/tests/no-rpath.sh
patchelf/tests/plain-fail.sh
patchelf/tests/plain-run.sh
patchelf/tests/set-interpreter-long.sh
patchelf/tests/set-interpreter-short.sh
patchelf/tests/set-rpath-library.sh
patchelf/tests/set-rpath.sh
patchelf/tests/shrink-rpath.sh
patchelf/tests/simple.c
patchelf/tests/soname.sh
patchelf/tests/.deps/bar.Po
patchelf/tests/.deps/big-dynstr.Po
patchelf/tests/.deps/foo.Po
patchelf/tests/.deps/main.Po
patchelf/tests/.deps/no_rpath-no-rpath.Po
patchelf/tests/.deps/simple-simple.Po
patchelf/tests/.deps/simple.Po
patchelf/tests/no-rpath-prebuild/no-rpath-amd64
patchelf/tests/no-rpath-prebuild/no-rpath-armel
patchelf/tests/no-rpath-prebuild/no-rpath-armhf
patchelf/tests/no-rpath-prebuild/no-rpath-hurd-i386
patchelf/tests/no-rpath-prebuild/no-rpath-i386
patchelf/tests/no-rpath-prebuild/no-rpath-ia64
pypatchelf.egg-info/PKG-INFO
pypatchelf.egg-info/SOURCES.txt
pypatchelf.egg-info/dependency_links.txt
pypatchelf.egg-info/entry_points.txt
pypatchelf.egg-info/not-zip-safe
pypatchelf.egg-info/pbr.json
pypatchelf.egg-info/top_level.txt