Metadata-Version: 1.1
Name: pypatchelf
Version: 0.9
Summary: A small utility to modify the dynamic linker and RPATH of ELF executables
Home-page: https://github.com/nixos/patchelf
Author: Robert T. McGibbon
Author-email: rmcgibbo@gmail.com
License: GPL
Platform: Linux
Classifier: Development Status :: 3 - Alpha
Classifier: Environment :: Console
Classifier: Intended Audience :: Developers
Classifier: License :: OSI Approved :: GNU General Public License v3 (GPLv3)
Classifier: Operating System :: POSIX :: Linux
Classifier: Topic :: Software Development
